eu/__init__.py
eu/softfire/__init__.py
eu/softfire/pd/__init__.py
eu/softfire/pd/core/PDManager.py
eu/softfire/pd/core/__init__.py
eu/softfire/pd/main/Manager.py
eu/softfire/pd/main/__init__.py
eu/softfire/pd/utils/__init__.py
eu/softfire/pd/utils/static_config.py
eu/softfire/pd/utils/utils.py
physical_device_manager-1.0.6.data/scripts/physical-device-manager
physical_device_manager-1.0.6.dist-info/DESCRIPTION.rst
physical_device_manager-1.0.6.dist-info/METADATA
physical_device_manager-1.0.6.dist-info/RECORD
physical_device_manager-1.0.6.dist-info/WHEEL
physical_device_manager-1.0.6.dist-info/metadata.json
physical_device_manager-1.0.6.dist-info/top_level.txt
